py_vol_surface/__init__.py
py_vol_surface/data_objects.py
py_vol_surface/defaults.py
py_vol_surface/exceptions.py
py_vol_surface/instruments.py
py_vol_surface/interpolation_engines.py
py_vol_surface/misc_widgets.py
py_vol_surface/plotting_engines.py
py_vol_surface/settings_widgets.py
py_vol_surface/surface_plotter.py
py_vol_surface/utils.py
py_vol_surface/workers.py
py_vol_surface/axis/__init__.py
py_vol_surface/axis/axis_utils.py
py_vol_surface/axis/axis_widgets.py
py_vol_surface/engines/__init__.py
py_vol_surface/engines/option_engines/base.py
py_vol_surface/engines/option_engines/black.py
py_vol_surface/engines/option_engines/black_scholes_merton.py
py_vol_surface/engines/yield_engines/__init__.py
py_vol_surface/engines/yield_engines/implied_engines.py
py_vol_surface/plot_views/__init__.py
py_vol_surface/plot_views/plot_views_utils.py
py_vol_surface/plot_views/view_2D.py
py_vol_surface/plot_views/view_3D.py
py_vol_surface/plotitems_3D/gl_plotitems.py
py_vol_surface/plotitems_3D/gl_plotitems_utils.py
py_vol_surface-0.0.2.1.2.dist-info/METADATA
py_vol_surface-0.0.2.1.2.dist-info/WHEEL
py_vol_surface-0.0.2.1.2.dist-info/top_level.txt
py_vol_surface-0.0.2.1.2.dist-info/RECORD
