Metadata-Version: 2.4
Name: py_vol_surface
Version: 0.0.2.1.2
Summary: A package the generates a realtime 3D volatility surface
Author-email: Ted Love <tedlove@victoriarivertrading.com>
License: MIT
Project-URL: Homepage, https://github.com/ted-love/py_vol_surface
Requires-Dist: numpy==2.1.3
Requires-Dist: pandas==2.2.3
Requires-Dist: PyOpenGL==3.1.9
Requires-Dist: pyqtgraph==0.13.7
Requires-Dist: PySide6==6.8.2.1
Provides-Extra: all
Requires-Dist: nest_asyncio==1.6.0; extra == "all"
Requires-Dist: pandas==2.2.3; extra == "all"
Requires-Dist: numba>=0.60.0; extra == "all"
Requires-Dist: py_vollib_vectorized==0.1.1; extra == "all"
Requires-Dist: PyOpenGL==3.1.9; extra == "all"
Requires-Dist: pyqtgraph==0.13.7; extra == "all"
Requires-Dist: PySide6==6.8.2.1; extra == "all"
Requires-Dist: requests==2.32.3; extra == "all"
Requires-Dist: websockets==15.0.1; extra == "all"
Requires-Dist: scipy==1.15.2; extra == "all"
